rayasdk/__init__.py
rayasdk/__main__.py
rayasdk/connect.py
rayasdk/constants.py
rayasdk/initializer.py
rayasdk/killer.py
rayasdk/logger.py
rayasdk/runner.py
rayasdk/scanner.py
rayasdk/simulator.py
rayasdk/container_handlers/__init__.py
rayasdk/container_handlers/docker_handler.py
rayasdk/template/__main__.py
rayasdk/template/app.py
rayasdk/template/manifest.json
rayasdk-1.0.10.dist-info/METADATA
rayasdk-1.0.10.dist-info/WHEEL
rayasdk-1.0.10.dist-info/entry_points.txt
rayasdk-1.0.10.dist-info/top_level.txt
rayasdk-1.0.10.dist-info/RECORD
