Metadata-Version: 2.1
Name: rayasdk
Version: 1.0.10
Summary: Raya SDK - Unlimited Robotics Software Development Kit
Home-page: 
Download-URL: 
Author: Unlimited Robotics
Author-email: camilo@unlimited-robotics.com
License: MIT
Keywords: robotics,unlimited-robotics,gary
Platform: UNKNOWN
Requires-Python: >=3.8
Requires-Dist: tabulate
Requires-Dist: importlib-metadata
Requires-Dist: tqdm
Requires-Dist: docker
Requires-Dist: progressbar
Requires-Dist: simple-file-checksum
